VindicateN/__init__.py
VindicateN/love.py
VindicateN/main.py
vindicaten-0.1.0.dist-info/METADATA
vindicaten-0.1.0.dist-info/WHEEL
vindicaten-0.1.0.dist-info/RECORD
