Metadata-Version: 2.1
Name: VindicateN
Version: 0.1.0
Summary: 
Author: why_zsr
Author-email: why3157@163.com
Requires-Python: >=3.9,<4.0
Classifier: Programming Language :: Python :: 3
Classifier: Programming Language :: Python :: 3.9
Classifier: Programming Language :: Python :: 3.10
Classifier: Programming Language :: Python :: 3.11
Classifier: Programming Language :: Python :: 3.12
Requires-Dist: requests (>=2.25.1,<3.0.0)
